market_calendars/__init__.py
market_calendars/calendar_registry.py
market_calendars/class_registry.py
market_calendars/exchange_china_sse.py
market_calendars/exchange_null.py
market_calendars/exchange_nyse.py
market_calendars/market_calendar.py
market_calendars/core/__init__.py
market_calendars/core/assert_utils.cp36-win_amd64.pyd
market_calendars/core/calendar.cp36-win_amd64.pyd
market_calendars/core/date.cp36-win_amd64.pyd
market_calendars/core/period.cp36-win_amd64.pyd
market_calendars/core/schedule.cp36-win_amd64.pyd
market_calendars/core/enums/__init__.py
market_calendars/core/enums/bizday_conventions.cp36-win_amd64.pyd
market_calendars/core/enums/date_generation.cp36-win_amd64.pyd
market_calendars/core/enums/months.cp36-win_amd64.pyd
market_calendars/core/enums/time_units.cp36-win_amd64.pyd
market_calendars/core/enums/weekdays.cp36-win_amd64.pyd
market_calendars/tests/__init__.py
market_calendars/tests/test_calendar_chinasse.py
market_calendars/tests/test_calendar_null.py
market_calendars/tests/test_calendar_nyse.py
market_calendars/tests/test_core_calendar.py
market_calendars/tests/test_core_date.py
market_calendars/tests/test_core_period.py
market_calendars/tests/test_core_schedule.py
market_calendars/tests/test_main.py
market_calendars-0.1.5.dist-info/METADATA
market_calendars-0.1.5.dist-info/RECORD
market_calendars-0.1.5.dist-info/WHEEL
market_calendars-0.1.5.dist-info/top_level.txt
