Metadata-Version: 2.1
Name: market-calendars
Version: 0.1.5
Summary: market_calendars 0.1.5
Home-page: https://github.com/iLampard/market_calendars
Author: iLampard
Author-email: UNKNOWN
License: UNKNOWN
Platform: UNKNOWN
Requires-Dist: cython (>=0.26.0)
Requires-Dist: numpy (>=1.10.1)
Requires-Dist: pandas (>=0.18.0)
Requires-Dist: scipy (>=0.18.0)
Requires-Dist: simpleutils (>=0.1.0)
Requires-Dist: six (>=1.10.0)
